<?xml version="1.0" encoding="utf-8"?>
<TextureAtlas imagePath="JusticeAngry.png">
	<!-- Created with Adobe Animate version 21.0.1.37179 -->
	<!-- http://www.adobe.com/products/animate.html -->
	<SubTexture name="Justice_downMADDANCE0000" x="0" y="0" width="560" height="856" frameX="0" frameY="-51" frameWidth="571" frameHeight="932"/>
	<SubTexture name="Justice_downMADDANCE0001" x="0" y="0" width="560" height="856" frameX="0" frameY="-51" frameWidth="571" frameHeight="932"/>
	<SubTexture name="Justice_downMADDANCE0002" x="562" y="0" width="550" height="873" frameX="-15" frameY="-49" frameWidth="571" frameHeight="932"/>
	<SubTexture name="Justice_downMADDANCE0003" x="562" y="0" width="550" height="873" frameX="-15" frameY="-49" frameWidth="571" frameHeight="932"/>
	<SubTexture name="Justice_downMADDANCE0004" x="1114" y="0" width="549" height="894" frameX="-22" frameY="-27" frameWidth="571" frameHeight="932"/>
	<SubTexture name="Justice_downMADDANCE0005" x="1114" y="0" width="549" height="894" frameX="-22" frameY="-27" frameWidth="571" frameHeight="932"/>
	<SubTexture name="Justice_downMADDANCE0006" x="1665" y="0" width="564" height="903" frameX="-7" frameY="-27" frameWidth="571" frameHeight="932"/>
	<SubTexture name="Justice_downMADDANCE0007" x="1665" y="0" width="564" height="903" frameX="-7" frameY="-27" frameWidth="571" frameHeight="932"/>
	<SubTexture name="Justice_downMADDANCE0008" x="2231" y="0" width="563" height="905" frameX="-8" frameY="-27" frameWidth="571" frameHeight="932"/>
	<SubTexture name="Justice_downMADDANCE0009" x="2231" y="0" width="563" height="905" frameX="-8" frameY="-27" frameWidth="571" frameHeight="932"/>
	<SubTexture name="Justice_downMADDANCE0010" x="2796" y="0" width="548" height="916" frameX="-21" frameY="0" frameWidth="571" frameHeight="932"/>
	<SubTexture name="Justice_downMADDANCE0011" x="2796" y="0" width="548" height="916" frameX="-21" frameY="0" frameWidth="571" frameHeight="932"/>
	<SubTexture name="Justice_idleMADDANCE0000" x="3346" y="0" width="551" height="939" frameX="-3" frameY="-6" frameWidth="563" frameHeight="950"/>
	<SubTexture name="Justice_idleMADDANCE0001" x="3346" y="0" width="551" height="939" frameX="-3" frameY="-6" frameWidth="563" frameHeight="950"/>
	<SubTexture name="Justice_idleMADDANCE0002" x="3899" y="0" width="561" height="941" frameX="-2" frameY="-6" frameWidth="563" frameHeight="950"/>
	<SubTexture name="Justice_idleMADDANCE0003" x="3899" y="0" width="561" height="941" frameX="-2" frameY="-6" frameWidth="563" frameHeight="950"/>
	<SubTexture name="Justice_idleMADDANCE0004" x="4462" y="0" width="552" height="935" frameX="-5" frameY="-7" frameWidth="563" frameHeight="950"/>
	<SubTexture name="Justice_idleMADDANCE0005" x="4462" y="0" width="552" height="935" frameX="-5" frameY="-7" frameWidth="563" frameHeight="950"/>
	<SubTexture name="Justice_idleMADDANCE0006" x="5016" y="0" width="534" height="939" frameX="0" frameY="-6" frameWidth="563" frameHeight="950"/>
	<SubTexture name="Justice_idleMADDANCE0007" x="5016" y="0" width="534" height="939" frameX="0" frameY="-6" frameWidth="563" frameHeight="950"/>
	<SubTexture name="Justice_idleMADDANCE0008" x="5552" y="0" width="521" height="948" frameX="-4" frameY="-2" frameWidth="563" frameHeight="950"/>
	<SubTexture name="Justice_idleMADDANCE0009" x="5552" y="0" width="521" height="948" frameX="-4" frameY="-2" frameWidth="563" frameHeight="950"/>
	<SubTexture name="Justice_idleMADDANCE0010" x="6075" y="0" width="512" height="946" frameX="-6" frameY="0" frameWidth="563" frameHeight="950"/>
	<SubTexture name="Justice_idleMADDANCE0011" x="6075" y="0" width="512" height="946" frameX="-6" frameY="0" frameWidth="563" frameHeight="950"/>
	<SubTexture name="Justice_leftMADDANCE0000" x="6589" y="0" width="480" height="966" frameX="0" frameY="0" frameWidth="496" frameHeight="971"/>
	<SubTexture name="Justice_leftMADDANCE0001" x="6589" y="0" width="480" height="966" frameX="0" frameY="0" frameWidth="496" frameHeight="971"/>
	<SubTexture name="Justice_leftMADDANCE0002" x="7071" y="0" width="477" height="967" frameX="-14" frameY="-1" frameWidth="496" frameHeight="971"/>
	<SubTexture name="Justice_leftMADDANCE0003" x="7071" y="0" width="477" height="967" frameX="-14" frameY="-1" frameWidth="496" frameHeight="971"/>
	<SubTexture name="Justice_leftMADDANCE0004" x="7550" y="0" width="470" height="960" frameX="-26" frameY="-3" frameWidth="496" frameHeight="971"/>
	<SubTexture name="Justice_leftMADDANCE0005" x="7550" y="0" width="470" height="960" frameX="-26" frameY="-3" frameWidth="496" frameHeight="971"/>
	<SubTexture name="Justice_leftMADDANCE0006" x="0" y="969" width="470" height="963" frameX="-26" frameY="-3" frameWidth="496" frameHeight="971"/>
	<SubTexture name="Justice_leftMADDANCE0007" x="0" y="969" width="470" height="963" frameX="-26" frameY="-3" frameWidth="496" frameHeight="971"/>
	<SubTexture name="Justice_leftMADDANCE0008" x="472" y="969" width="470" height="968" frameX="-26" frameY="-3" frameWidth="496" frameHeight="971"/>
	<SubTexture name="Justice_leftMADDANCE0009" x="472" y="969" width="470" height="968" frameX="-26" frameY="-3" frameWidth="496" frameHeight="971"/>
	<SubTexture name="Justice_leftMADDANCE0010" x="944" y="969" width="470" height="964" frameX="-26" frameY="-3" frameWidth="496" frameHeight="971"/>
	<SubTexture name="Justice_leftMADDANCE0011" x="944" y="969" width="470" height="964" frameX="-26" frameY="-3" frameWidth="496" frameHeight="971"/>
	<SubTexture name="Justice_rightMADDANCE0000" x="1416" y="969" width="615" height="959" frameX="-9" frameY="0" frameWidth="629" frameHeight="964"/>
	<SubTexture name="Justice_rightMADDANCE0001" x="1416" y="969" width="615" height="959" frameX="-9" frameY="0" frameWidth="629" frameHeight="964"/>
	<SubTexture name="Justice_rightMADDANCE0002" x="2033" y="969" width="615" height="950" frameX="-9" frameY="-11" frameWidth="629" frameHeight="964"/>
	<SubTexture name="Justice_rightMADDANCE0003" x="2033" y="969" width="615" height="950" frameX="-9" frameY="-11" frameWidth="629" frameHeight="964"/>
	<SubTexture name="Justice_rightMADDANCE0004" x="2650" y="969" width="627" height="940" frameX="-2" frameY="-16" frameWidth="629" frameHeight="964"/>
	<SubTexture name="Justice_rightMADDANCE0005" x="2650" y="969" width="627" height="940" frameX="-2" frameY="-16" frameWidth="629" frameHeight="964"/>
	<SubTexture name="Justice_rightMADDANCE0006" x="3279" y="969" width="629" height="943" frameX="0" frameY="-16" frameWidth="629" frameHeight="964"/>
	<SubTexture name="Justice_rightMADDANCE0007" x="3279" y="969" width="629" height="943" frameX="0" frameY="-16" frameWidth="629" frameHeight="964"/>
	<SubTexture name="Justice_rightMADDANCE0008" x="3910" y="969" width="623" height="948" frameX="-6" frameY="-16" frameWidth="629" frameHeight="964"/>
	<SubTexture name="Justice_rightMADDANCE0009" x="4535" y="969" width="623" height="948" frameX="-6" frameY="-16" frameWidth="629" frameHeight="964"/>
	<SubTexture name="Justice_rightMADDANCE0010" x="5160" y="969" width="619" height="944" frameX="0" frameY="-16" frameWidth="629" frameHeight="964"/>
	<SubTexture name="Justice_rightMADDANCE0011" x="5160" y="969" width="619" height="944" frameX="0" frameY="-16" frameWidth="629" frameHeight="964"/>
	<SubTexture name="Justice_taunt_CATCH0000" x="5781" y="969" width="558" height="939" frameX="-3" frameY="-10" frameWidth="629" frameHeight="954"/>
	<SubTexture name="Justice_taunt_CATCH0001" x="5781" y="969" width="558" height="939" frameX="-3" frameY="-10" frameWidth="629" frameHeight="954"/>
	<SubTexture name="Justice_taunt_CATCH0002" x="6341" y="969" width="570" height="941" frameX="-2" frameY="-10" frameWidth="629" frameHeight="954"/>
	<SubTexture name="Justice_taunt_CATCH0003" x="6341" y="969" width="570" height="941" frameX="-2" frameY="-10" frameWidth="629" frameHeight="954"/>
	<SubTexture name="Justice_taunt_CATCH0004" x="6913" y="969" width="558" height="935" frameX="-5" frameY="-11" frameWidth="629" frameHeight="954"/>
	<SubTexture name="Justice_taunt_CATCH0005" x="6913" y="969" width="558" height="935" frameX="-5" frameY="-11" frameWidth="629" frameHeight="954"/>
	<SubTexture name="Justice_taunt_CATCH0006" x="7473" y="969" width="543" height="945" frameX="0" frameY="-4" frameWidth="629" frameHeight="954"/>
	<SubTexture name="Justice_taunt_CATCH0007" x="7473" y="969" width="543" height="945" frameX="0" frameY="-4" frameWidth="629" frameHeight="954"/>
	<SubTexture name="Justice_taunt_CATCH0008" x="0" y="1939" width="608" height="952" frameX="-4" frameY="-2" frameWidth="629" frameHeight="954"/>
	<SubTexture name="Justice_taunt_CATCH0009" x="0" y="1939" width="608" height="952" frameX="-4" frameY="-2" frameWidth="629" frameHeight="954"/>
	<SubTexture name="Justice_taunt_CATCH0010" x="610" y="1939" width="619" height="950" frameX="-6" frameY="0" frameWidth="629" frameHeight="954"/>
	<SubTexture name="Justice_taunt_CATCH0011" x="610" y="1939" width="619" height="950" frameX="-6" frameY="0" frameWidth="629" frameHeight="954"/>
	<SubTexture name="Justice_taunt_CATCH0012" x="1231" y="1939" width="628" height="948" frameX="-1" frameY="-1" frameWidth="629" frameHeight="954"/>
	<SubTexture name="Justice_taunt_CATCH0013" x="1231" y="1939" width="628" height="948" frameX="-1" frameY="-1" frameWidth="629" frameHeight="954"/>
	<SubTexture name="Justice_taunt_CATCH0014" x="1861" y="1939" width="617" height="951" frameX="-5" frameY="0" frameWidth="629" frameHeight="954"/>
	<SubTexture name="Justice_taunt_CATCH0015" x="1861" y="1939" width="617" height="951" frameX="-5" frameY="0" frameWidth="629" frameHeight="954"/>
	<SubTexture name="Justice_taunt_DROWN0000" x="2480" y="1939" width="551" height="939" frameX="-76" frameY="-21" frameWidth="727" frameHeight="965"/>
	<SubTexture name="Justice_taunt_DROWN0001" x="2480" y="1939" width="551" height="939" frameX="-76" frameY="-21" frameWidth="727" frameHeight="965"/>
	<SubTexture name="Justice_taunt_DROWN0002" x="3033" y="1939" width="567" height="930" frameX="-77" frameY="-32" frameWidth="727" frameHeight="965"/>
	<SubTexture name="Justice_taunt_DROWN0003" x="3033" y="1939" width="567" height="930" frameX="-77" frameY="-32" frameWidth="727" frameHeight="965"/>
	<SubTexture name="Justice_taunt_DROWN0004" x="3602" y="1939" width="586" height="923" frameX="-71" frameY="-34" frameWidth="727" frameHeight="965"/>
	<SubTexture name="Justice_taunt_DROWN0005" x="3602" y="1939" width="586" height="923" frameX="-71" frameY="-34" frameWidth="727" frameHeight="965"/>
	<SubTexture name="Justice_taunt_DROWN0006" x="4190" y="1939" width="604" height="927" frameX="-64" frameY="-33" frameWidth="727" frameHeight="965"/>
	<SubTexture name="Justice_taunt_DROWN0007" x="4190" y="1939" width="604" height="927" frameX="-64" frameY="-33" frameWidth="727" frameHeight="965"/>
	<SubTexture name="Justice_taunt_DROWN0008" x="4796" y="1939" width="615" height="932" frameX="-65" frameY="-33" frameWidth="727" frameHeight="965"/>
	<SubTexture name="Justice_taunt_DROWN0009" x="4796" y="1939" width="615" height="932" frameX="-65" frameY="-33" frameWidth="727" frameHeight="965"/>
	<SubTexture name="Justice_taunt_DROWN0010" x="5413" y="1939" width="630" height="932" frameX="-65" frameY="-29" frameWidth="727" frameHeight="965"/>
	<SubTexture name="Justice_taunt_DROWN0011" x="5413" y="1939" width="630" height="932" frameX="-65" frameY="-29" frameWidth="727" frameHeight="965"/>
	<SubTexture name="Justice_taunt_DROWN0012" x="6045" y="1939" width="623" height="934" frameX="-57" frameY="-26" frameWidth="727" frameHeight="965"/>
	<SubTexture name="Justice_taunt_DROWN0013" x="6045" y="1939" width="623" height="934" frameX="-57" frameY="-26" frameWidth="727" frameHeight="965"/>
	<SubTexture name="Justice_taunt_DROWN0014" x="6670" y="1939" width="700" height="941" frameX="-20" frameY="-21" frameWidth="727" frameHeight="965"/>
	<SubTexture name="Justice_taunt_DROWN0015" x="6670" y="1939" width="700" height="941" frameX="-20" frameY="-21" frameWidth="727" frameHeight="965"/>
	<SubTexture name="Justice_taunt_DROWN0016" x="7372" y="1939" width="708" height="948" frameX="-8" frameY="-9" frameWidth="727" frameHeight="965"/>
	<SubTexture name="Justice_taunt_DROWN0017" x="7372" y="1939" width="708" height="948" frameX="-8" frameY="-9" frameWidth="727" frameHeight="965"/>
	<SubTexture name="Justice_taunt_DROWN0018" x="0" y="2893" width="721" height="951" frameX="-6" frameY="-9" frameWidth="727" frameHeight="965"/>
	<SubTexture name="Justice_taunt_DROWN0019" x="0" y="2893" width="721" height="951" frameX="-6" frameY="-9" frameWidth="727" frameHeight="965"/>
	<SubTexture name="Justice_taunt_DROWN0020" x="723" y="2893" width="700" height="956" frameX="-16" frameY="-9" frameWidth="727" frameHeight="965"/>
	<SubTexture name="Justice_taunt_DROWN0021" x="723" y="2893" width="700" height="956" frameX="-16" frameY="-9" frameWidth="727" frameHeight="965"/>
	<SubTexture name="Justice_taunt_DROWN0022" x="1425" y="2893" width="712" height="953" frameX="-15" frameY="-8" frameWidth="727" frameHeight="965"/>
	<SubTexture name="Justice_taunt_DROWN0023" x="1425" y="2893" width="712" height="953" frameX="-15" frameY="-8" frameWidth="727" frameHeight="965"/>
	<SubTexture name="Justice_taunt_DROWN0024" x="2139" y="2893" width="716" height="953" frameX="0" frameY="-7" frameWidth="727" frameHeight="965"/>
	<SubTexture name="Justice_taunt_DROWN0025" x="2139" y="2893" width="716" height="953" frameX="0" frameY="-7" frameWidth="727" frameHeight="965"/>
	<SubTexture name="Justice_taunt_DROWN0026" x="2857" y="2893" width="706" height="955" frameX="-21" frameY="-7" frameWidth="727" frameHeight="965"/>
	<SubTexture name="Justice_taunt_DROWN0027" x="2857" y="2893" width="706" height="955" frameX="-21" frameY="-7" frameWidth="727" frameHeight="965"/>
	<SubTexture name="Justice_taunt_DROWN0028" x="3565" y="2893" width="707" height="950" frameX="-9" frameY="-7" frameWidth="727" frameHeight="965"/>
	<SubTexture name="Justice_taunt_DROWN0029" x="3565" y="2893" width="707" height="950" frameX="-9" frameY="-7" frameWidth="727" frameHeight="965"/>
	<SubTexture name="Justice_taunt_DROWN0030" x="4274" y="2893" width="722" height="953" frameX="-5" frameY="-7" frameWidth="727" frameHeight="965"/>
	<SubTexture name="Justice_taunt_DROWN0031" x="4274" y="2893" width="722" height="953" frameX="-5" frameY="-7" frameWidth="727" frameHeight="965"/>
	<SubTexture name="Justice_taunt_DROWN0032" x="4998" y="2893" width="702" height="965" frameX="-14" frameY="0" frameWidth="727" frameHeight="965"/>
	<SubTexture name="Justice_taunt_DROWN0033" x="4998" y="2893" width="702" height="965" frameX="-14" frameY="0" frameWidth="727" frameHeight="965"/>
	<SubTexture name="Justice_taunt_DROWN0034" x="5702" y="2893" width="668" height="960" frameX="-34" frameY="-1" frameWidth="727" frameHeight="965"/>
	<SubTexture name="Justice_taunt_DROWN0035" x="5702" y="2893" width="668" height="960" frameX="-34" frameY="-1" frameWidth="727" frameHeight="965"/>
	<SubTexture name="Justice_taunt_DROWN0036" x="6372" y="2893" width="662" height="959" frameX="-29" frameY="-1" frameWidth="727" frameHeight="965"/>
	<SubTexture name="Justice_taunt_DROWN0037" x="6372" y="2893" width="662" height="959" frameX="-29" frameY="-1" frameWidth="727" frameHeight="965"/>
	<SubTexture name="Justice_taunt_DROWN0038" x="7036" y="2893" width="668" height="958" frameX="-34" frameY="-4" frameWidth="727" frameHeight="965"/>
	<SubTexture name="Justice_taunt_DROWN0039" x="7036" y="2893" width="668" height="958" frameX="-34" frameY="-4" frameWidth="727" frameHeight="965"/>
	<SubTexture name="Justice_taunt_DROWN0040" x="0" y="3860" width="662" height="950" frameX="-29" frameY="-7" frameWidth="727" frameHeight="965"/>
	<SubTexture name="Justice_taunt_DROWN0041" x="0" y="3860" width="662" height="950" frameX="-29" frameY="-7" frameWidth="727" frameHeight="965"/>
	<SubTexture name="Justice_taunt_DROWN0042" x="664" y="3860" width="669" height="952" frameX="-33" frameY="-8" frameWidth="727" frameHeight="965"/>
	<SubTexture name="Justice_taunt_DROWN0043" x="664" y="3860" width="669" height="952" frameX="-33" frameY="-8" frameWidth="727" frameHeight="965"/>
	<SubTexture name="Justice_taunt_DROWN0044" x="1335" y="3860" width="664" height="958" frameX="-27" frameY="-7" frameWidth="727" frameHeight="965"/>
	<SubTexture name="Justice_taunt_DROWN0045" x="1335" y="3860" width="664" height="958" frameX="-27" frameY="-7" frameWidth="727" frameHeight="965"/>
	<SubTexture name="Justice_taunt_ENOUGH0000" x="2001" y="3860" width="551" height="939" frameX="-5" frameY="-20" frameWidth="810" frameHeight="964"/>
	<SubTexture name="Justice_taunt_ENOUGH0001" x="2001" y="3860" width="551" height="939" frameX="-5" frameY="-20" frameWidth="810" frameHeight="964"/>
	<SubTexture name="Justice_taunt_ENOUGH0002" x="2554" y="3860" width="569" height="941" frameX="-4" frameY="-20" frameWidth="810" frameHeight="964"/>
	<SubTexture name="Justice_taunt_ENOUGH0003" x="2554" y="3860" width="569" height="941" frameX="-4" frameY="-20" frameWidth="810" frameHeight="964"/>
	<SubTexture name="Justice_taunt_ENOUGH0004" x="3125" y="3860" width="558" height="935" frameX="-7" frameY="-21" frameWidth="810" frameHeight="964"/>
	<SubTexture name="Justice_taunt_ENOUGH0005" x="3125" y="3860" width="558" height="935" frameX="-7" frameY="-21" frameWidth="810" frameHeight="964"/>
	<SubTexture name="Justice_taunt_ENOUGH0006" x="3685" y="3860" width="547" height="945" frameX="-2" frameY="-14" frameWidth="810" frameHeight="964"/>
	<SubTexture name="Justice_taunt_ENOUGH0007" x="3685" y="3860" width="547" height="945" frameX="-2" frameY="-14" frameWidth="810" frameHeight="964"/>
	<SubTexture name="Justice_taunt_ENOUGH0008" x="4234" y="3860" width="531" height="952" frameX="-6" frameY="-12" frameWidth="810" frameHeight="964"/>
	<SubTexture name="Justice_taunt_ENOUGH0009" x="4234" y="3860" width="531" height="952" frameX="-6" frameY="-12" frameWidth="810" frameHeight="964"/>
	<SubTexture name="Justice_taunt_ENOUGH0010" x="4767" y="3860" width="521" height="950" frameX="-8" frameY="-10" frameWidth="810" frameHeight="964"/>
	<SubTexture name="Justice_taunt_ENOUGH0011" x="4767" y="3860" width="521" height="950" frameX="-8" frameY="-10" frameWidth="810" frameHeight="964"/>
	<SubTexture name="Justice_taunt_ENOUGH0012" x="5290" y="3860" width="516" height="948" frameX="-5" frameY="-11" frameWidth="810" frameHeight="964"/>
	<SubTexture name="Justice_taunt_ENOUGH0013" x="5290" y="3860" width="516" height="948" frameX="-5" frameY="-11" frameWidth="810" frameHeight="964"/>
	<SubTexture name="Justice_taunt_ENOUGH0014" x="5808" y="3860" width="516" height="949" frameX="-10" frameY="-12" frameWidth="810" frameHeight="964"/>
	<SubTexture name="Justice_taunt_ENOUGH0015" x="5808" y="3860" width="516" height="949" frameX="-10" frameY="-12" frameWidth="810" frameHeight="964"/>
	<SubTexture name="Justice_taunt_ENOUGH0016" x="6326" y="3860" width="518" height="944" frameX="-5" frameY="-12" frameWidth="810" frameHeight="964"/>
	<SubTexture name="Justice_taunt_ENOUGH0017" x="6326" y="3860" width="518" height="944" frameX="-5" frameY="-12" frameWidth="810" frameHeight="964"/>
	<SubTexture name="Justice_taunt_ENOUGH0018" x="6846" y="3860" width="522" height="946" frameX="0" frameY="-13" frameWidth="810" frameHeight="964"/>
	<SubTexture name="Justice_taunt_ENOUGH0019" x="6846" y="3860" width="522" height="946" frameX="0" frameY="-13" frameWidth="810" frameHeight="964"/>
	<SubTexture name="Justice_taunt_ENOUGH0020" x="7370" y="3860" width="661" height="951" frameX="-3" frameY="-13" frameWidth="810" frameHeight="964"/>
	<SubTexture name="Justice_taunt_ENOUGH0021" x="0" y="4820" width="789" height="964" frameX="-11" frameY="0" frameWidth="810" frameHeight="964"/>
	<SubTexture name="Justice_taunt_ENOUGH0022" x="791" y="4820" width="798" height="957" frameX="-12" frameY="-3" frameWidth="810" frameHeight="964"/>
	<SubTexture name="Justice_taunt_ENOUGH0023" x="791" y="4820" width="798" height="957" frameX="-12" frameY="-3" frameWidth="810" frameHeight="964"/>
	<SubTexture name="Justice_taunt_ENOUGH0024" x="1591" y="4820" width="744" height="947" frameX="-6" frameY="-12" frameWidth="810" frameHeight="964"/>
	<SubTexture name="Justice_taunt_ENOUGH0025" x="1591" y="4820" width="744" height="947" frameX="-6" frameY="-12" frameWidth="810" frameHeight="964"/>
	<SubTexture name="Justice_taunt_ENOUGH0026" x="2337" y="4820" width="686" height="945" frameX="-9" frameY="-16" frameWidth="810" frameHeight="964"/>
	<SubTexture name="Justice_taunt_ENOUGH0027" x="2337" y="4820" width="686" height="945" frameX="-9" frameY="-16" frameWidth="810" frameHeight="964"/>
	<SubTexture name="Justice_taunt_ENOUGH0028" x="3025" y="4820" width="675" height="937" frameX="-4" frameY="-19" frameWidth="810" frameHeight="964"/>
	<SubTexture name="Justice_taunt_ENOUGH0029" x="3025" y="4820" width="675" height="937" frameX="-4" frameY="-19" frameWidth="810" frameHeight="964"/>
	<SubTexture name="Justice_taunt_ENOUGH0030" x="3702" y="4820" width="674" height="935" frameX="0" frameY="-24" frameWidth="810" frameHeight="964"/>
	<SubTexture name="Justice_taunt_ENOUGH0031" x="3702" y="4820" width="674" height="935" frameX="0" frameY="-24" frameWidth="810" frameHeight="964"/>
	<SubTexture name="Justice_taunt_ENOUGH0032" x="4378" y="4820" width="667" height="940" frameX="-5" frameY="-24" frameWidth="810" frameHeight="964"/>
	<SubTexture name="Justice_taunt_ENOUGH0033" x="4378" y="4820" width="667" height="940" frameX="-5" frameY="-24" frameWidth="810" frameHeight="964"/>
	<SubTexture name="Justice_upMADDANCE0000" x="5047" y="4820" width="547" height="951" frameX="0" frameY="0" frameWidth="548" frameHeight="956"/>
	<SubTexture name="Justice_upMADDANCE0001" x="5047" y="4820" width="547" height="951" frameX="0" frameY="0" frameWidth="548" frameHeight="956"/>
	<SubTexture name="Justice_upMADDANCE0002" x="5596" y="4820" width="537" height="946" frameX="-9" frameY="-1" frameWidth="548" frameHeight="956"/>
	<SubTexture name="Justice_upMADDANCE0003" x="5596" y="4820" width="537" height="946" frameX="-9" frameY="-1" frameWidth="548" frameHeight="956"/>
	<SubTexture name="Justice_upMADDANCE0004" x="6135" y="4820" width="538" height="943" frameX="-10" frameY="-5" frameWidth="548" frameHeight="956"/>
	<SubTexture name="Justice_upMADDANCE0005" x="6135" y="4820" width="538" height="943" frameX="-10" frameY="-5" frameWidth="548" frameHeight="956"/>
	<SubTexture name="Justice_upMADDANCE0006" x="6675" y="4820" width="545" height="946" frameX="-3" frameY="-5" frameWidth="548" frameHeight="956"/>
	<SubTexture name="Justice_upMADDANCE0007" x="6675" y="4820" width="545" height="946" frameX="-3" frameY="-5" frameWidth="548" frameHeight="956"/>
	<SubTexture name="Justice_upMADDANCE0008" x="7222" y="4820" width="545" height="951" frameX="-3" frameY="-5" frameWidth="548" frameHeight="956"/>
	<SubTexture name="Justice_upMADDANCE0009" x="7222" y="4820" width="545" height="951" frameX="-3" frameY="-5" frameWidth="548" frameHeight="956"/>
	<SubTexture name="Justice_upMADDANCE0010" x="0" y="5786" width="532" height="943" frameX="-11" frameY="-9" frameWidth="548" frameHeight="956"/>
	<SubTexture name="Justice_upMADDANCE0011" x="0" y="5786" width="532" height="943" frameX="-11" frameY="-9" frameWidth="548" frameHeight="956"/>
</TextureAtlas>
